[
  {
    "JEDAPEHMCPJ": 1001,
    "JBDAFDHMKPA": 1073279233,
    "LKIPAHNOPDL": "223001",
    "KKEDINHDBMA": [
      10011,
      10012,
      10013
    ],
    "KBEGEDAGNOI": 95,
    "EIFDFGELJBH": 3000,
    "ADDMBJEJANG": 1500,
    "LBEKIAFPGAL": 2100,
    "LFIODDHLJLK": [
      12010201,
      12010202,
      12010203
    ],
    "CCKJGHCBNOC": 10
  },
  {
    "JEDAPEHMCPJ": 1002,
    "JBDAFDHMKPA": 1006197233,
    "LKIPAHNOPDL": "223002",
    "KKEDINHDBMA": [
      10021,
      10022,
      10023
    ],
    "KBEGEDAGNOI": 95,
    "EIFDFGELJBH": 3000,
    "ADDMBJEJANG": 1500,
    "LBEKIAFPGAL": 2100,
    "LFIODDHLJLK": [
      12010204,
      12010205,
      12010206
    ],
    "CCKJGHCBNOC": 10
  },
  {
    "JEDAPEHMCPJ": 1003,
    "JBDAFDHMKPA": 2707384737,
    "LKIPAHNOPDL": "223003",
    "KKEDINHDBMA": [
      10031,
      10032,
      10033,
      10034
    ],
    "KBEGEDAGNOI": 95,
    "EIFDFGELJBH": 4000,
    "ADDMBJEJANG": 2000,
    "LBEKIAFPGAL": 2800,
    "LFIODDHLJLK": [
      12010207,
      12010208,
      12010209
    ],
    "CCKJGHCBNOC": 10
  },
  {
    "JEDAPEHMCPJ": 1004,
    "JBDAFDHMKPA": 4038017649,
    "LKIPAHNOPDL": "223004",
    "KKEDINHDBMA": [
      10041,
      10042,
      10043,
      10044
    ],
    "KBEGEDAGNOI": 75,
    "EIFDFGELJBH": 4000,
    "ADDMBJEJANG": 2000,
    "LBEKIAFPGAL": 2800,
    "LFIODDHLJLK": [
      12010210,
      12010211,
      12010212
    ],
    "CCKJGHCBNOC": 10
  },
  {
    "JEDAPEHMCPJ": 1005,
    "JBDAFDHMKPA": 3910695769,
    "LKIPAHNOPDL": "223005",
    "KKEDINHDBMA": [
      10051,
      10052,
      10053,
      10054,
      10055
    ],
    "KBEGEDAGNOI": 95,
    "EIFDFGELJBH": 5000,
    "ADDMBJEJANG": 2500,
    "LBEKIAFPGAL": 3500,
    "LFIODDHLJLK": [
      12010213,
      12010214,
      12010215
    ],
    "CCKJGHCBNOC": 20
  },
  {
    "JEDAPEHMCPJ": 1006,
    "JBDAFDHMKPA": 2824132353,
    "LKIPAHNOPDL": "223006",
    "KKEDINHDBMA": [
      10061,
      10062,
      10063,
      10064,
      10065
    ],
    "KBEGEDAGNOI": 95,
    "EIFDFGELJBH": 5000,
    "ADDMBJEJANG": 2500,
    "LBEKIAFPGAL": 3500,
    "LFIODDHLJLK": [
      12010216,
      12010217,
      12010218
    ],
    "CCKJGHCBNOC": 20
  }
]