[
  {},
  {
    "FIMKPHPNKOI": 1,
    "IOCMEIPPLDE": 15,
    "CFGIOOJOIHD": 1.5,
    "INIEFDICDCM": 1.5
  },
  {
    "FIMKPHPNKOI": 2,
    "IOCMEIPPLDE": 28,
    "CFGIOOJOIHD": 3,
    "INIEFDICDCM": 3
  },
  {
    "FIMKPHPNKOI": 3,
    "IOCMEIPPLDE": 60,
    "CFGIOOJOIHD": 6,
    "INIEFDICDCM": 6
  },
  {
    "FIMKPHPNKOI": 4,
    "IOCMEIPPLDE": 73,
    "CFGIOOJOIHD": 7.5,
    "INIEFDICDCM": 7.5
  },
  {
    "FIMKPHPNKOI": 5,
    "IOCMEIPPLDE": 105,
    "CFGIOOJOIHD": 10.5,
    "INIEFDICDCM": 10.5
  },
  {
    "FIMKPHPNKOI": 6,
    "IOCMEIPPLDE": 118,
    "CFGIOOJOIHD": 12,
    "INIEFDICDCM": 12
  }
]